nonebot_plugin_repeep/__init__.py
nonebot_plugin_repeep/config.py
nonebot_plugin_repeep/ua_parse.py
nonebot_plugin_repeep-0.1.4.dist-info/LICENSE
nonebot_plugin_repeep-0.1.4.dist-info/WHEEL
nonebot_plugin_repeep-0.1.4.dist-info/METADATA
nonebot_plugin_repeep-0.1.4.dist-info/RECORD
