Metadata-Version: 2.1
Name: nonebot-plugin-repeep
Version: 0.1.4
Summary: A plugin based on nonebot2, which is used to display the current peeping user information in QQ.
Home-page: https://github.com/p0ise/nonebot-plugin-repeep
License: GPL-3.0-or-later
Author: p0ise
Author-email: changelf@163.com
Requires-Python: >=3.8,<4.0
Classifier: License :: OSI Approved :: GNU General Public License v3 or later (GPLv3+)
Classifier: Programming Language :: Python :: 3
Classifier: Programming Language :: Python :: 3.8
Classifier: Programming Language :: Python :: 3.9
Classifier: Programming Language :: Python :: 3.10
Classifier: Programming Language :: Python :: 3.11
Requires-Dist: httpx (>=0.23.1,<0.24.0)
Requires-Dist: nonebot-adapter-onebot (>=2.1.5,<3.0.0)
Requires-Dist: nonebot2 (>=2.0.0-beta.1,<3.0.0)
Requires-Dist: user-agents (>=2.2.0,<3.0.0)
Project-URL: Repository, https://github.com/p0ise/nonebot-plugin-repeep
